[
	{
		"id": 1,
		"dataCadastro": "2022-04-27T19:21:42.004Z",
		"dataAtualizacao": "2022-04-27T19:21:42.004Z",
		"local_id": 1,
		"quadra_tipo_id": 1,
		"imagem": "url",
		"nome": "Pavê no fim de Ano",
		"largura": "",
		"comprimento": "",
		"descricao": "Pavê no fim de Ano é uma quadra muito interessante visto que é um grande doce",
		"piso": "",
		"precoHora": 120,
		"precoMeiaHora": 120,
		"avaliacao": 2.3,
		"chuteira_tipos_aceito": "",
		"tem_vestiario": false,
		"tem_banheiro": false,
		"tem_chuveiro": false,
		"tem_bebedouro": false,
		"tem_coletes": false,
		"tem_juiz": false,
		"tem_cantina": false,
		"tem_areaAlimentacao": false,
		"tem_chuteira": false,
		"tem_bola": false,	
		"foto": {
			"id": 1,
			"url": "/img/QuadraCards/quadra.jpg"
		},
		"fotos": [
			{
				"id": 1,
				"url": "https://via.placeholder.com/1024x768"
			},
			{
				"id": 2,
				"url": "img/quadras/01/2.jpg"
			},
			{
				"id": 3,
				"url": "img/quadras/01/3.jpg"
			}
		]
	},
	{
		"id": 2,
		"dataCadastro": "2022-04-27T19:21:44.412Z",
		"dataAtualizacao": "2022-04-27T19:21:44.412Z",
		"local_id": 2,
		"quadra_tipo_id": 2,
		"imagem": "url",
		"nome": "Urso Rosa",
		"largura": "",
		"comprimento": "",
		"descricao": "Quem já viu na sua vida um futebol com um urso cor de Rosa?",
		"piso": "",
		"precoHora": 219.99,
		"precoMeiaHora": 120,
		"avaliacao": 3.5,
		"chuteira_tipos_aceito": "",
		"tem_vestiario": false,
		"tem_banheiro": false,
		"tem_chuveiro": false,
		"tem_bebedouro": false,
		"tem_coletes": false,
		"tem_juiz": false,
		"tem_cantina": false,
		"tem_areaAlimentacao": false,
		"tem_chuteira": false,
		"tem_bola": false,
		"foto": {
			"id": 1,
			"url": "/img/QuadraCards/quadra1.jpg"
		},
		"fotos": [
			{
				"id": 1,
				"url": "https://via.placeholder.com/1024x768"
			},
			{
				"id": 2,
				"url": "img/quadras/01/2.jpg"
			},
			{
				"id": 3,
				"url": "img/quadras/01/3.jpg"
			}
		]
	},
	{
		"id": 3,
		"dataCadastro": "2022-04-27T19:21:45.299Z",
		"dataAtualizacao": "2022-04-27T19:21:45.299Z",
		"local_id": 2,
		"quadra_tipo_id": 3,
		"imagem": "url",
		"nome": "Doce sem Coco",
		"largura": "",
		"comprimento": "",
		"descricao": "Uma quadra agradável, bonita, e o mais importante, não tem coco em seu meio!!",
		"piso": "",
		"precoHora": 98.9,
		"precoMeiaHora": 120,
		"avaliacao": 5,
		"chuteira_tipos_aceito": "",
		"tem_vestiario": false,
		"tem_banheiro": false,
		"tem_chuveiro": false,
		"tem_bebedouro": false,
		"tem_coletes": false,
		"tem_juiz": false,
		"tem_cantina": false,
		"tem_areaAlimentacao": false,
		"tem_chuteira": false,
		"tem_bola": false,
		"foto": {
			"id": 1,
			"url": "/img/QuadraCards/quadra2.jpg"
		},
		"fotos": [
			{
				"id": 1,
				"url": "https://via.placeholder.com/1024x768"
			},
			{
				"id": 2,
				"url": "img/quadras/01/2.jpg"
			},
			{
				"id": 3,
				"url": "img/quadras/01/3.jpg"
			}
		]
	},
	{
		"id": 4,
		"dataCadastro": "2022-04-27T19:21:45.299Z",
		"dataAtualizacao": "2022-04-27T19:21:45.299Z",
		"local_id": 3,
		"quadra_tipo_id": 4,
		"imagem": "url",
		"nome": "JoGolfinho's",
		"largura": "",
		"comprimento": "",
		"descricao": "Como se pode jogar com golfinhos saltitantes e tão habilidosos como estes",
		"piso": "",
		"precoHora": 125.43,
		"precoMeiaHora": 120,
		"avaliacao": 1.1,
		"chuteira_tipos_aceito": "",
		"tem_vestiario": false,
		"tem_banheiro": false,
		"tem_chuveiro": false,
		"tem_bebedouro": false,
		"tem_coletes": false,
		"tem_juiz": false,
		"tem_cantina": false,
		"tem_areaAlimentacao": false,
		"tem_chuteira": false,
		"tem_bola": false,
		"foto": {
			"id": 1,
			"url": "/img/QuadraCards/quadra3.jpg"
		},
		"fotos": [
			{
				"id": 1,
				"url": "https://via.placeholder.com/1024x768"
			},
			{
				"id": 2,
				"url": "img/quadras/01/2.jpg"
			},
			{
				"id": 3,
				"url": "img/quadras/01/3.jpg"
			}
		]
	},
	{
		"id": 5,
		"dataCadastro": "2022-06-22T17:04:55.574Z",
		"dataAtualizacao": "2022-06-22T17:04:55.574Z",
		"local_id": 17,
		"quadra_tipo_id": 1,
		"imagem": "url",
		"nome": "",
		"largura": "",
		"comprimento": "",
		"descricao": "",
		"piso": "",
		"precoHora": 0,
		"precoMeiaHora": 0,
		"avaliacao": 0,
		"chuteira_tipos_aceito": "",
		"tem_vestiario": false,
		"tem_banheiro": false,
		"tem_chuveiro": false,
		"tem_bebedouro": false,
		"tem_coletes": false,
		"tem_juiz": false,
		"tem_cantina": false,
		"tem_areaAlimentacao": false,
		"tem_chuteira": false,
		"tem_bola": false,
		"foto": null,
		"fotos": []
	}
]